examples/example.ipynb
examples/example.py
nbhint/__init__.py
nbhint/nbhint.py
nbhint-0.1.2.dist-info/METADATA
nbhint-0.1.2.dist-info/WHEEL
nbhint-0.1.2.dist-info/licenses/LICENSE.txt
nbhint-0.1.2.dist-info/RECORD
