Metadata-Version: 2.1
Name: nbHint
Version: 0.1.2
Summary: Python package to check structure of python code building upon AST.
Project-URL: Homepage, https://github.com/smfloery/nbHint
Project-URL: Bug Tracker, https://github.com/smfloery/nbHint/issues
Author-email: Felix Meixner <e12027400@student.tuwien.ac.at>, Sebastian Mikolka-Flöry <sebastian.mikolka@geo.tuwien.ac.at>
License-File: LICENSE.txt
Classifier: License :: OSI Approved :: MIT License
Classifier: Operating System :: OS Independent
Classifier: Programming Language :: Python :: 3
Requires-Python: >=3.8
Requires-Dist: nbformat
